trenchripper/DetectPeaks.py
trenchripper/__init__.py
trenchripper/analysis.py
trenchripper/cluster.py
trenchripper/drift_detection.py
trenchripper/interactive.py
trenchripper/kymograph.py
trenchripper/kymograph_template_match.py
trenchripper/metrics.py
trenchripper/ndextract.py
trenchripper/phase_tracking.py
trenchripper/segment.py
trenchripper/setup.py
trenchripper/tplot.py
trenchripper/tracking.py
trenchripper/trcluster.py
trenchripper/unet.py
trenchripper/utils.py
trenchripper/trenchripper/DetectPeaks.py
trenchripper/trenchripper/__init__.py
trenchripper/trenchripper/analysis.py
trenchripper/trenchripper/drift_detection.py
trenchripper/trenchripper/interactive.py
trenchripper/trenchripper/kymograph.py
trenchripper/trenchripper/kymograph_template_match.py
trenchripper/trenchripper/metrics.py
trenchripper/trenchripper/ndextract.py
trenchripper/trenchripper/phase_tracking.py
trenchripper/trenchripper/segment.py
trenchripper/trenchripper/tplot.py
trenchripper/trenchripper/tracking.py
trenchripper/trenchripper/trcluster.py
trenchripper/trenchripper/unet.py
trenchripper/trenchripper/utils.py
TrenchRipper-0.2.1.dist-info/LICENSE
TrenchRipper-0.2.1.dist-info/METADATA
TrenchRipper-0.2.1.dist-info/WHEEL
TrenchRipper-0.2.1.dist-info/top_level.txt
TrenchRipper-0.2.1.dist-info/RECORD
