Metadata-Version: 2.1
Name: TrenchRipper
Version: 0.2.1
Summary: UNKNOWN
Home-page: https://github.com/DanielScottEaton/TrenchRipper
Author: Daniel Eaton
License: UNKNOWN
Platform: UNKNOWN
Requires-Python: >=3.7
Requires-Dist: pandas (==1.0.3)
Requires-Dist: numpy (>=1.18.1)
Requires-Dist: bokeh (==1.4.0)
Requires-Dist: h5py (>=2.10.0)
Requires-Dist: h5py-cache (==1.0)
Requires-Dist: scipy (>=1.4.1)
Requires-Dist: scikit-image (>=0.16.2)
Requires-Dist: jupyter-client (==6.1.3)
Requires-Dist: jupyter-core (==4.6.3)
Requires-Dist: jupyterlab (==2.0.1)
Requires-Dist: jupyterlab-server (==1.0.7)
Requires-Dist: jupyter-server-proxy (==1.3.2)
Requires-Dist: matplotlib
Requires-Dist: dask (==2.12.0)
Requires-Dist: distributed (==2.12.0)
Requires-Dist: dask-jobqueue (==0.7.0)
Requires-Dist: dask-labextension (==2.0.1)
Requires-Dist: tifffile (>=2020.2.16)
Requires-Dist: ipywidgets (==7.5.1)
Requires-Dist: pulp (>=1.6.8)
Requires-Dist: fastparquet (>=0.3.3)
Requires-Dist: torch (>=1.4.0)
Requires-Dist: torchvision (>=0.5.0)
Requires-Dist: tables (>=3.6.1)
Requires-Dist: scikit-learn (>=0.22.1)
Requires-Dist: seaborn (==0.10.0)
Requires-Dist: nd2reader (==3.2.3)
Requires-Dist: parse (==1.15.0)
Requires-Dist: qgrid (==1.3.1)
Requires-Dist: opencv-python
